{"neighbors":[{"id":"8119","name":"Jahan Dotson","slug":"jahan-dotson","team":"PHI","position":"WR","posRank":136,"ppg":1.9},{"id":"2197","name":"Brandin Cooks","slug":"brandin-cooks","team":"BUF","position":"WR","posRank":137,"ppg":1.9},{"id":"6154","name":"David Sills","slug":"david-sills","team":"ATL","position":"WR","posRank":138,"ppg":1.8},{"id":"5086","name":"Marquez Valdes-Scantling","slug":"marquez-valdes-scantling","team":"PIT","position":"WR","posRank":140,"ppg":1.8},{"id":"12542","name":"Efton Chism","slug":"efton-chism","team":"NE","position":"WR","posRank":141,"ppg":1.7},{"id":"7039","name":"Cody White","slug":"cody-white","team":"SEA","position":"WR","posRank":142,"ppg":1.7}],"currentRank":139,"season":2025,"format":"standard","position":"WR"}