{"neighbors":[{"id":"6528","name":"Joey Slye","slug":"joey-slye","team":"TEN","position":"K","posRank":22,"ppg":8},{"id":"650","name":"Nick Folk","slug":"nick-folk","team":"NYJ","position":"K","posRank":23,"ppg":7.9},{"id":"3678","name":"Wil Lutz","slug":"wil-lutz","team":"DEN","position":"K","posRank":24,"ppg":7.6},{"id":"503","name":"Graham Gano","slug":"graham-gano","team":"NYG","position":"K","posRank":26,"ppg":7.6},{"id":"11058","name":"Blake Grupe","slug":"blake-grupe","team":"IND","position":"K","posRank":27,"ppg":7.6},{"id":"10955","name":"Chad Ryland","slug":"chad-ryland","team":"ARI","position":"K","posRank":28,"ppg":7.2}],"currentRank":25,"season":2025,"format":"half","position":"K"}