{"neighbors":[{"id":"9493","name":"Puka Nacua","slug":"puka-nacua","team":"LAR","position":"WR","posRank":1,"ppg":23.4},{"id":"9488","name":"Jaxon Smith-Njigba","slug":"jaxon-smith-njigba","team":"SEA","position":"WR","posRank":2,"ppg":21.2},{"id":"7547","name":"Amon-Ra St. Brown","slug":"amon-ra-st-brown","team":"DET","position":"WR","posRank":4,"ppg":19.1},{"id":"10229","name":"Rashee Rice","slug":"rashee-rice","team":"KC","position":"WR","posRank":5,"ppg":18.8},{"id":"8137","name":"George Pickens","slug":"george-pickens","team":"DAL","position":"WR","posRank":6,"ppg":17.2}],"currentRank":3,"season":2025,"format":"ppr","position":"WR"}