{"neighbors":[{"id":"8204","name":"Bo Melton","slug":"bo-melton","team":"GB","position":"WR","posRank":154,"ppg":1.7},{"id":"11623","name":"Jordan Whittington","slug":"jordan-whittington","team":"LAR","position":"WR","posRank":155,"ppg":1.7},{"id":"6427","name":"Ashton Dulin","slug":"ashton-dulin","team":"IND","position":"WR","posRank":156,"ppg":1.5},{"id":"12670","name":"KeAndre Lambert-Smith","slug":"keandre-lambert-smith","team":"LAC","position":"WR","posRank":158,"ppg":1.4},{"id":"11921","name":"Xavier Weaver","slug":"xavier-weaver","team":"ARI","position":"WR","posRank":159,"ppg":1.3},{"id":"12541","name":"Dont'e Thornton","slug":"donte-thornton","team":"LV","position":"WR","posRank":160,"ppg":1.2}],"currentRank":157,"season":2025,"format":"half","position":"WR"}