{"neighbors":[{"id":"4080","name":"Zay Jones","slug":"zay-jones","team":"ARI","position":"WR","posRank":117,"ppg":3},{"id":"2374","name":"Tyler Lockett","slug":"tyler-lockett","team":"LV","position":"WR","posRank":118,"ppg":3},{"id":"8135","name":"Treylon Burks","slug":"treylon-burks","team":"WAS","position":"WR","posRank":119,"ppg":3},{"id":"6699","name":"Gunner Olszewski","slug":"gunner-olszewski","team":"NYG","position":"WR","posRank":121,"ppg":2.9},{"id":"8117","name":"Jalen Tolbert","slug":"jalen-tolbert","team":"DAL","position":"WR","posRank":122,"ppg":2.9},{"id":"12503","name":"Isaiah Bond","slug":"isaiah-bond","team":"CLE","position":"WR","posRank":123,"ppg":2.9}],"currentRank":120,"season":2025,"format":"half","position":"WR"}