{"id":"9228","slug":"bryce-young","name":"Bryce Young","position":"QB","team":"CAR","season":2026,"advStats":[{"rank":21,"playerId":"9228","playerName":"Bryce Young","position":"QB","team":"CAR","age":24,"season":2025,"games":16,"attempts":478,"completions":304,"completionPct":63.6,"passingYards":3011,"yardsPerCatch":6.3,"passingTouchdowns":23,"interceptions":11,"fantasyPoints":218,"airYards":3102,"completedAirYards":1466,"completedAirYardsPerCompletion":4.8,"deepAttemptPct":7.7,"epaPerPlay":-0.03,"successRate":42.6,"cpoe":1,"throwaways":32,"battedPasses":9,"poorThrows":73,"badThrowPct":16.4,"onTargetPct":77.9,"passesDropped":18,"passes10Plus":114,"passes20Plus":39,"passes30Plus":13,"passes40Plus":4,"passes50Plus":1,"longestPass":54,"rushAttempts":54,"rushYards":216,"rushTouchdowns":2,"redZoneAttempts":72,"scrambleRate":6.1,"yardsPerScramble":6.7,"fumbles":6,"sacks":27,"sackYardsLost":202,"pocketTime":2.4,"timeToThrow":2.83,"blitzes":127,"hurries":54,"knockdowns":48,"pressurePct":24},{"rank":23,"playerId":"9228","playerName":"Bryce Young","position":"QB","team":"CAR","age":23,"season":2024,"games":14,"attempts":384,"completions":234,"completionPct":60.9,"passingYards":2403,"yardsPerCatch":6.26,"passingTouchdowns":15,"interceptions":9,"fantasyPoints":195,"airYards":3358,"completedAirYards":1434,"completedAirYardsPerCompletion":6.1,"deepAttemptPct":11.6,"epaPerPlay":-0.03,"successRate":40.1,"cpoe":0.7,"throwaways":25,"battedPasses":1,"poorThrows":80,"badThrowPct":22.3,"onTargetPct":71.9,"passesDropped":15,"passes10Plus":96,"passes20Plus":30,"passes30Plus":11,"passes40Plus":3,"passes50Plus":1,"longestPass":83,"rushAttempts":43,"rushYards":249,"rushTouchdowns":6,"redZoneAttempts":63,"scrambleRate":8.2,"yardsPerScramble":6.9,"fumbles":4,"sacks":29,"sackYardsLost":186,"pocketTime":2.3,"timeToThrow":2.79,"blitzes":136,"hurries":53,"knockdowns":38,"pressurePct":26.7},{"rank":20,"playerId":"9228","playerName":"Bryce Young","position":"QB","team":"CAR","age":22,"season":2023,"games":16,"attempts":527,"completions":315,"completionPct":59.8,"passingYards":2877,"yardsPerCatch":5.46,"passingTouchdowns":11,"interceptions":10,"fantasyPoints":156.4,"airYards":4009,"completedAirYards":1540,"completedAirYardsPerCompletion":4.89,"deepAttemptPct":9.8,"epaPerPlay":-0.232,"successRate":36.6,"cpoe":-1.4,"throwaways":46,"battedPasses":6,"poorThrows":103,"badThrowPct":21.5,"onTargetPct":73.3,"passesDropped":23,"passes10Plus":109,"passes20Plus":26,"passes30Plus":10,"passes40Plus":4,"passes50Plus":0,"longestPass":48,"rushAttempts":39,"rushYards":253,"rushTouchdowns":0,"redZoneAttempts":52,"scrambleRate":null,"yardsPerScramble":null,"fumbles":11,"sacks":62,"sackYardsLost":477,"pocketTime":2.5,"timeToThrow":2.9,"blitzes":166,"hurries":38,"knockdowns":50,"pressurePct":24.2}],"fantasyProsUrl":"https://www.fantasypros.com/nfl/players/bryce-young.php","cbsUrl":"https://www.cbssports.com/fantasy/football/news/2026-outlook-bryce-young/"}