{"id":"3634","slug":"kalif-raymond","name":"Kalif Raymond","position":"WR","team":"CHI","season":2026,"advStats":[{"rank":97,"playerId":"3634","playerName":"Kalif Raymond","position":"WR","team":"DET","age":31,"season":2025,"games":15,"snapPct":36.6,"routes":214,"routePct":34.6,"targets":30,"targetsPerRouteRun":0.14,"targetSharePct":5.5,"airYardsPerTarget":5.63,"airYardsPerReception":7.04,"airYardsSharePct":4.5,"wopr":0.114,"receptions":24,"redZoneTargets":2,"endZoneTargets":1,"catchPct":80,"receivingYards":289,"totalYards":308,"yardsPerReception":12.04,"yardsBeforeCatchPerReception":5.5,"yardsAfterCatchPerReception":6.54,"yardsAfterContactPerReception":null,"yardsPerRouteRun":1.35,"receivingTouchdowns":1,"epaPerPlay":0.507,"successRate":66.7,"contestedCatchRate":null,"fantasyPoints":42.8,"avoidedTackleRate":4.2,"brokenTackles":1,"drops":0,"catchableTargets":24,"dropPct":0,"interceptionsWhenTargeted":0,"fumbles":0,"receptions10Plus":11,"receptions20Plus":4,"receptions30Plus":1,"receptions40Plus":0,"receptions50Plus":0,"longestReception":30},{"rank":116,"playerId":"3634","playerName":"Kalif Raymond","position":"WR","team":"DET","age":30,"season":2024,"games":12,"snapPct":27.1,"routes":123,"routePct":21.2,"targets":22,"targetsPerRouteRun":0.179,"targetSharePct":4.2,"airYardsPerTarget":8,"airYardsPerReception":10.35,"airYardsSharePct":5,"wopr":0.099,"receptions":17,"redZoneTargets":2,"endZoneTargets":1,"catchPct":77.3,"receivingYards":215,"totalYards":215,"yardsPerReception":12.65,"yardsBeforeCatchPerReception":4.59,"yardsAfterCatchPerReception":8.06,"yardsAfterContactPerReception":null,"yardsPerRouteRun":1.75,"receivingTouchdowns":2,"epaPerPlay":0.604,"successRate":63.6,"contestedCatchRate":null,"fantasyPoints":39.5,"avoidedTackleRate":0,"brokenTackles":0,"drops":0,"catchableTargets":17,"dropPct":0,"interceptionsWhenTargeted":0,"fumbles":0,"receptions10Plus":8,"receptions20Plus":3,"receptions30Plus":1,"receptions40Plus":0,"receptions50Plus":0,"longestReception":38},{"rank":67,"playerId":"3634","playerName":"Kalif Raymond","position":"WR","team":"DET","age":29,"season":2023,"games":17,"snapPct":29.5,"routes":230,"routePct":36.3,"targets":44,"targetsPerRouteRun":0.191,"targetSharePct":7.7,"airYardsPerTarget":8.82,"airYardsPerReception":11.09,"airYardsSharePct":9.5,"wopr":0.181,"receptions":35,"redZoneTargets":4,"endZoneTargets":0,"catchPct":79.5,"receivingYards":489,"totalYards":564,"yardsPerReception":13.97,"yardsBeforeCatchPerReception":7.86,"yardsAfterCatchPerReception":6.11,"yardsAfterContactPerReception":null,"yardsPerRouteRun":2.13,"receivingTouchdowns":1,"epaPerPlay":0.68,"successRate":68.2,"contestedCatchRate":null,"fantasyPoints":62.4,"avoidedTackleRate":2.9,"brokenTackles":1,"drops":2,"catchableTargets":37,"dropPct":4.5,"interceptionsWhenTargeted":0,"fumbles":0,"receptions10Plus":23,"receptions20Plus":9,"receptions30Plus":3,"receptions40Plus":2,"receptions50Plus":0,"longestReception":41}],"fantasyProsUrl":"https://www.fantasypros.com/nfl/players/kalif-raymond.php","cbsUrl":"https://www.cbssports.com/fantasy/football/news/2026-outlook-kalif-raymond/"}