{"updated_at":"2026-06-16T00:00:00Z","season":2024,"position":"TE","columns":[{"key":"rank","label":"Rank","type":"number","defaultVisible":true},{"key":"playerName","label":"Player","type":"string","defaultVisible":true},{"key":"team","label":"Team","type":"string","defaultVisible":true},{"key":"games","label":"G","type":"number","defaultVisible":true},{"key":"snapPct","label":"Snap %","type":"decimal","defaultVisible":true},{"key":"targets","label":"Tgt","type":"number","defaultVisible":true},{"key":"targetsPerGame","label":"Tgt/G","type":"decimal","defaultVisible":true},{"key":"targetSharePct","label":"Tgt Share","type":"decimal","defaultVisible":true},{"key":"receptions","label":"Rec","type":"number","defaultVisible":true},{"key":"receivingYards","label":"Rec Yds","type":"number","defaultVisible":true},{"key":"receivingYardsPerGame","label":"Rec Y/G","type":"decimal","defaultVisible":true},{"key":"receivingTouchdowns","label":"Rec TD","type":"number","defaultVisible":true},{"key":"catchPct","label":"Catch %","type":"decimal","defaultVisible":true},{"key":"yardsPerReception","label":"Y/Rec","type":"decimal","defaultVisible":true},{"key":"yardsPerTarget","label":"Y/Tgt","type":"decimal","defaultVisible":true},{"key":"fantasyPoints","label":"FP (PPR)","type":"number","defaultVisible":true},{"key":"ppg","label":"PPG","type":"decimal","defaultVisible":true}],"rows":[{"playerId":"11604","playerName":"Brock Bowers","team":"LV","games":17,"snapPct":85.1,"fantasyPoints":262.7,"ppg":15.5,"targets":153,"targetsPerGame":9,"targetSharePct":25.9,"receptions":112,"receivingYards":1194,"receivingYardsPerGame":70.2,"receivingTouchdowns":5,"catchPct":73.2,"yardsPerReception":10.66,"yardsPerTarget":7.8,"rank":1},{"playerId":"8130","playerName":"Trey McBride","team":"ARI","games":16,"snapPct":90.1,"fantasyPoints":249.8,"ppg":15.6,"targets":147,"targetsPerGame":9.2,"targetSharePct":29.3,"receptions":111,"receivingYards":1146,"receivingYardsPerGame":71.6,"receivingTouchdowns":2,"catchPct":75.5,"yardsPerReception":10.32,"yardsPerTarget":7.8,"rank":2},{"playerId":"4217","playerName":"George Kittle","team":"SF","games":15,"snapPct":85.5,"fantasyPoints":236.6,"ppg":15.8,"targets":94,"targetsPerGame":6.3,"targetSharePct":22,"receptions":78,"receivingYards":1106,"receivingYardsPerGame":73.7,"receivingTouchdowns":8,"catchPct":83,"yardsPerReception":14.18,"yardsPerTarget":11.77,"rank":3},{"playerId":"4144","playerName":"Jonnu Smith","team":"MIA","games":17,"snapPct":55,"fantasyPoints":222.3,"ppg":13.1,"targets":111,"targetsPerGame":6.5,"targetSharePct":20,"receptions":88,"receivingYards":884,"receivingYardsPerGame":52,"receivingTouchdowns":8,"catchPct":79.3,"yardsPerReception":10.05,"yardsPerTarget":7.96,"rank":4},{"playerId":"1466","playerName":"Travis Kelce","team":"KC","games":16,"snapPct":84.4,"fantasyPoints":195.4,"ppg":12.2,"targets":133,"targetsPerGame":8.3,"targetSharePct":24.1,"receptions":97,"receivingYards":823,"receivingYardsPerGame":51.4,"receivingTouchdowns":3,"catchPct":72.9,"yardsPerReception":8.48,"yardsPerTarget":6.19,"rank":5},{"playerId":"5012","playerName":"Mark Andrews","team":"BAL","games":17,"snapPct":61.4,"fantasyPoints":188.8,"ppg":11.1,"targets":69,"targetsPerGame":4.1,"targetSharePct":15.3,"receptions":55,"receivingYards":673,"receivingYardsPerGame":39.6,"receivingTouchdowns":11,"catchPct":79.7,"yardsPerReception":12.24,"yardsPerTarget":9.75,"rank":6},{"playerId":"1339","playerName":"Zach Ertz","team":"WAS","games":17,"snapPct":66.3,"fantasyPoints":177.4,"ppg":10.4,"targets":91,"targetsPerGame":5.4,"targetSharePct":18.1,"receptions":66,"receivingYards":654,"receivingYardsPerGame":38.5,"receivingTouchdowns":7,"catchPct":72.5,"yardsPerReception":9.91,"yardsPerTarget":7.19,"rank":7},{"playerId":"10859","playerName":"Sam LaPorta","team":"DET","games":16,"snapPct":85.3,"fantasyPoints":174.6,"ppg":10.9,"targets":83,"targetsPerGame":5.2,"targetSharePct":17,"receptions":60,"receivingYards":726,"receivingYardsPerGame":45.4,"receivingTouchdowns":7,"catchPct":72.3,"yardsPerReception":12.1,"yardsPerTarget":8.75,"rank":8},{"playerId":"7600","playerName":"Pat Freiermuth","team":"PIT","games":17,"snapPct":68.7,"fantasyPoints":168.3,"ppg":9.9,"targets":78,"targetsPerGame":4.6,"targetSharePct":17,"receptions":65,"receivingYards":653,"receivingYardsPerGame":38.4,"receivingTouchdowns":7,"catchPct":83.3,"yardsPerReception":10.05,"yardsPerTarget":8.37,"rank":9},{"playerId":"9484","playerName":"Tucker Kraft","team":"GB","games":17,"snapPct":85.3,"fantasyPoints":163.3,"ppg":9.6,"targets":70,"targetsPerGame":4.1,"targetSharePct":15.1,"receptions":50,"receivingYards":707,"receivingYardsPerGame":41.6,"receivingTouchdowns":7,"catchPct":71.4,"yardsPerReception":14.14,"yardsPerTarget":10.1,"rank":10},{"playerId":"4033","playerName":"David Njoku","team":"CLE","games":11,"snapPct":75.3,"fantasyPoints":148.5,"ppg":13.5,"targets":97,"targetsPerGame":8.8,"targetSharePct":22.8,"receptions":64,"receivingYards":505,"receivingYardsPerGame":45.9,"receivingTouchdowns":5,"catchPct":66,"yardsPerReception":7.89,"yardsPerTarget":5.21,"rank":11},{"playerId":"3214","playerName":"Hunter Henry","team":"NE","games":16,"snapPct":81.1,"fantasyPoints":145.4,"ppg":9.1,"targets":97,"targetsPerGame":6.1,"targetSharePct":20.6,"receptions":66,"receivingYards":674,"receivingYardsPerGame":42.1,"receivingTouchdowns":2,"catchPct":68,"yardsPerReception":10.21,"yardsPerTarget":6.95,"rank":12},{"playerId":"4993","playerName":"Mike Gesicki","team":"CIN","games":17,"snapPct":46,"fantasyPoints":141.5,"ppg":8.3,"targets":83,"targetsPerGame":4.9,"targetSharePct":13.2,"receptions":65,"receivingYards":665,"receivingYardsPerGame":39.1,"receivingTouchdowns":2,"catchPct":78.3,"yardsPerReception":10.23,"yardsPerTarget":8.01,"rank":13},{"playerId":"8111","playerName":"Cade Otton","team":"TB","games":14,"snapPct":92.4,"fantasyPoints":140.6,"ppg":10,"targets":87,"targetsPerGame":6.2,"targetSharePct":19,"receptions":59,"receivingYards":600,"receivingYardsPerGame":42.9,"receivingTouchdowns":4,"catchPct":67.8,"yardsPerReception":10.17,"yardsPerTarget":6.9,"rank":14},{"playerId":"7553","playerName":"Kyle Pitts","team":"ATL","games":17,"snapPct":61.9,"fantasyPoints":131.2,"ppg":7.7,"targets":74,"targetsPerGame":4.4,"targetSharePct":13.7,"receptions":47,"receivingYards":602,"receivingYardsPerGame":35.4,"receivingTouchdowns":4,"catchPct":63.5,"yardsPerReception":12.81,"yardsPerTarget":8.14,"rank":15},{"playerId":"8131","playerName":"Isaiah Likely","team":"BAL","games":16,"snapPct":59.9,"fantasyPoints":123.7,"ppg":7.7,"targets":58,"targetsPerGame":3.6,"targetSharePct":13.8,"receptions":42,"receivingYards":477,"receivingYardsPerGame":29.8,"receivingTouchdowns":6,"catchPct":72.4,"yardsPerReception":11.36,"yardsPerTarget":8.22,"rank":16},{"playerId":"7002","playerName":"Juwan Johnson","team":"NO","games":17,"snapPct":64.1,"fantasyPoints":122.8,"ppg":7.2,"targets":66,"targetsPerGame":3.9,"targetSharePct":12.9,"receptions":50,"receivingYards":548,"receivingYardsPerGame":32.2,"receivingTouchdowns":3,"catchPct":75.8,"yardsPerReception":10.96,"yardsPerTarget":8.3,"rank":17},{"playerId":"5133","playerName":"Tyler Conklin","team":"NYJ","games":16,"snapPct":79.9,"fantasyPoints":121.9,"ppg":7.6,"targets":72,"targetsPerGame":4.5,"targetSharePct":12.8,"receptions":51,"receivingYards":449,"receivingYardsPerGame":28.1,"receivingTouchdowns":4,"catchPct":70.8,"yardsPerReception":8.8,"yardsPerTarget":6.24,"rank":18},{"playerId":"6826","playerName":"Cole Kmet","team":"CHI","games":17,"snapPct":87.5,"fantasyPoints":120.4,"ppg":7.1,"targets":55,"targetsPerGame":3.2,"targetSharePct":10.4,"receptions":47,"receivingYards":474,"receivingYardsPerGame":27.9,"receivingTouchdowns":4,"catchPct":85.5,"yardsPerReception":10.09,"yardsPerTarget":8.62,"rank":19},{"playerId":"5001","playerName":"Dalton Schultz","team":"HOU","games":17,"snapPct":78.1,"fantasyPoints":118.2,"ppg":7,"targets":85,"targetsPerGame":5,"targetSharePct":15.6,"receptions":53,"receivingYards":532,"receivingYardsPerGame":31.3,"receivingTouchdowns":2,"catchPct":62.4,"yardsPerReception":10.04,"yardsPerTarget":6.26,"rank":20},{"playerId":"8210","playerName":"Chig Okonkwo","team":"TEN","games":17,"snapPct":60.8,"fantasyPoints":113.6,"ppg":6.7,"targets":70,"targetsPerGame":4.1,"targetSharePct":13.8,"receptions":52,"receivingYards":479,"receivingYardsPerGame":28.2,"receivingTouchdowns":2,"catchPct":74.3,"yardsPerReception":9.21,"yardsPerTarget":6.84,"rank":21},{"playerId":"7828","playerName":"Noah Gray","team":"KC","games":17,"snapPct":57.8,"fantasyPoints":113.3,"ppg":6.7,"targets":49,"targetsPerGame":2.9,"targetSharePct":8.6,"receptions":40,"receivingYards":437,"receivingYardsPerGame":25.7,"receivingTouchdowns":5,"catchPct":81.6,"yardsPerReception":10.93,"yardsPerTarget":8.92,"rank":22},{"playerId":"5010","playerName":"Will Dissly","team":"LAC","games":15,"snapPct":56.8,"fantasyPoints":110.1,"ppg":7.3,"targets":64,"targetsPerGame":4.3,"targetSharePct":15.1,"receptions":50,"receivingYards":481,"receivingYardsPerGame":32.1,"receivingTouchdowns":2,"catchPct":78.1,"yardsPerReception":9.62,"yardsPerTarget":7.52,"rank":23},{"playerId":"3202","playerName":"Austin Hooper","team":"NE","games":17,"snapPct":52.6,"fantasyPoints":108.6,"ppg":6.4,"targets":59,"targetsPerGame":3.5,"targetSharePct":11.8,"receptions":45,"receivingYards":476,"receivingYardsPerGame":28,"receivingTouchdowns":3,"catchPct":76.3,"yardsPerReception":10.58,"yardsPerTarget":8.07,"rank":24},{"playerId":"8110","playerName":"Jake Ferguson","team":"DAL","games":14,"snapPct":64.2,"fantasyPoints":104.4,"ppg":7.5,"targets":86,"targetsPerGame":6.1,"targetSharePct":17.4,"receptions":59,"receivingYards":494,"receivingYardsPerGame":35.3,"receivingTouchdowns":0,"catchPct":68.6,"yardsPerReception":8.37,"yardsPerTarget":5.74,"rank":25},{"playerId":"4381","playerName":"Taysom Hill","team":"NO","games":8,"snapPct":42.1,"fantasyPoints":104.3,"ppg":13,"targets":31,"targetsPerGame":3.9,"targetSharePct":14,"receptions":23,"receivingYards":187,"receivingYardsPerGame":23.4,"receivingTouchdowns":0,"catchPct":74.2,"yardsPerReception":8.13,"yardsPerTarget":6.03,"rank":26},{"playerId":"5857","playerName":"Noah Fant","team":"SEA","games":14,"snapPct":63.5,"fantasyPoints":104,"ppg":7.4,"targets":64,"targetsPerGame":4.6,"targetSharePct":13.4,"receptions":48,"receivingYards":500,"receivingYardsPerGame":35.7,"receivingTouchdowns":1,"catchPct":75,"yardsPerReception":10.42,"yardsPerTarget":7.81,"rank":27},{"playerId":"5022","playerName":"Dallas Goedert","team":"PHI","games":10,"snapPct":66.2,"fantasyPoints":103.6,"ppg":10.4,"targets":52,"targetsPerGame":5.2,"targetSharePct":19.3,"receptions":42,"receivingYards":496,"receivingYardsPerGame":49.6,"receivingTouchdowns":2,"catchPct":80.8,"yardsPerReception":11.81,"yardsPerTarget":9.54,"rank":28},{"playerId":"5985","playerName":"Foster Moreau","team":"NO","games":17,"snapPct":69.1,"fantasyPoints":103.3,"ppg":6.1,"targets":43,"targetsPerGame":2.5,"targetSharePct":8.4,"receptions":32,"receivingYards":413,"receivingYardsPerGame":24.3,"receivingTouchdowns":5,"catchPct":74.4,"yardsPerReception":12.91,"yardsPerTarget":9.6,"rank":29},{"playerId":"10236","playerName":"Dalton Kincaid","team":"BUF","games":13,"snapPct":56.7,"fantasyPoints":100.8,"ppg":7.8,"targets":75,"targetsPerGame":5.8,"targetSharePct":20.2,"receptions":44,"receivingYards":448,"receivingYardsPerGame":34.5,"receivingTouchdowns":2,"catchPct":58.7,"yardsPerReception":10.18,"yardsPerTarget":5.97,"rank":30},{"playerId":"9480","playerName":"Brenton Strange","team":"JAX","games":17,"snapPct":55.7,"fantasyPoints":91.1,"ppg":5.4,"targets":53,"targetsPerGame":3.1,"targetSharePct":10.2,"receptions":40,"receivingYards":411,"receivingYardsPerGame":24.2,"receivingTouchdowns":2,"catchPct":75.5,"yardsPerReception":10.28,"yardsPerTarget":7.75,"rank":31},{"playerId":"5032","playerName":"Jordan Akins","team":"CLE","games":17,"snapPct":38.6,"fantasyPoints":91,"ppg":5.4,"targets":58,"targetsPerGame":3.4,"targetSharePct":9.1,"receptions":40,"receivingYards":390,"receivingYardsPerGame":22.9,"receivingTouchdowns":2,"catchPct":69,"yardsPerReception":9.75,"yardsPerTarget":6.72,"rank":32},{"playerId":"4066","playerName":"Evan Engram","team":"JAX","games":9,"snapPct":71.5,"fantasyPoints":89.5,"ppg":9.9,"targets":64,"targetsPerGame":7.1,"targetSharePct":25.1,"receptions":47,"receivingYards":365,"receivingYardsPerGame":40.6,"receivingTouchdowns":1,"catchPct":73.4,"yardsPerReception":7.77,"yardsPerTarget":5.7,"rank":33},{"playerId":"5844","playerName":"T.J. Hockenson","team":"MIN","games":10,"snapPct":61,"fantasyPoints":86.5,"ppg":8.7,"targets":62,"targetsPerGame":6.2,"targetSharePct":18.4,"receptions":41,"receivingYards":455,"receivingYardsPerGame":45.5,"receivingTouchdowns":0,"catchPct":66.1,"yardsPerReception":11.1,"yardsPerTarget":7.34,"rank":34},{"playerId":"11603","playerName":"AJ Barner","team":"SEA","games":17,"snapPct":45.5,"fantasyPoints":78.5,"ppg":4.6,"targets":38,"targetsPerGame":2.2,"targetSharePct":6.7,"receptions":30,"receivingYards":245,"receivingYardsPerGame":14.4,"receivingTouchdowns":4,"catchPct":78.9,"yardsPerReception":8.17,"yardsPerTarget":6.45,"rank":35},{"playerId":"11600","playerName":"Ja'Tavion Sanders","team":"CAR","games":16,"snapPct":55.1,"fantasyPoints":73.2,"ppg":4.6,"targets":43,"targetsPerGame":2.7,"targetSharePct":9,"receptions":33,"receivingYards":342,"receivingYardsPerGame":21.4,"receivingTouchdowns":1,"catchPct":76.7,"yardsPerReception":10.36,"yardsPerTarget":7.95,"rank":36},{"playerId":"11597","playerName":"Theo Johnson","team":"NYG","games":12,"snapPct":84.2,"fantasyPoints":68.1,"ppg":5.7,"targets":43,"targetsPerGame":3.6,"targetSharePct":11.1,"receptions":29,"receivingYards":331,"receivingYardsPerGame":27.6,"receivingTouchdowns":1,"catchPct":67.4,"yardsPerReception":11.41,"yardsPerTarget":7.7,"rank":37},{"playerId":"5973","playerName":"Josh Oliver","team":"MIN","games":15,"snapPct":55.6,"fantasyPoints":65.8,"ppg":4.4,"targets":28,"targetsPerGame":1.9,"targetSharePct":6.2,"receptions":22,"receivingYards":258,"receivingYardsPerGame":17.2,"receivingTouchdowns":3,"catchPct":78.6,"yardsPerReception":11.73,"yardsPerTarget":9.21,"rank":38},{"playerId":"6865","playerName":"Colby Parkinson","team":"LAR","games":17,"snapPct":55.1,"fantasyPoints":65.4,"ppg":3.8,"targets":49,"targetsPerGame":2.9,"targetSharePct":9.1,"receptions":30,"receivingYards":294,"receivingYardsPerGame":17.3,"receivingTouchdowns":1,"catchPct":61.2,"yardsPerReception":9.8,"yardsPerTarget":6,"rank":39},{"playerId":"10212","playerName":"Josh Whyle","team":"TEN","games":17,"snapPct":31.5,"fantasyPoints":60.8,"ppg":3.6,"targets":37,"targetsPerGame":2.2,"targetSharePct":7.3,"receptions":28,"receivingYards":248,"receivingYardsPerGame":14.6,"receivingTouchdowns":1,"catchPct":75.7,"yardsPerReception":8.86,"yardsPerTarget":6.7,"rank":40},{"playerId":"8177","playerName":"Grant Calcaterra","team":"PHI","games":17,"snapPct":66.2,"fantasyPoints":59.8,"ppg":3.5,"targets":30,"targetsPerGame":1.8,"targetSharePct":7.2,"receptions":24,"receivingYards":298,"receivingYardsPerGame":17.5,"receivingTouchdowns":1,"catchPct":80,"yardsPerReception":12.42,"yardsPerTarget":9.93,"rank":41},{"playerId":"5906","playerName":"Dawson Knox","team":"BUF","games":16,"snapPct":60.5,"fantasyPoints":59.1,"ppg":3.7,"targets":33,"targetsPerGame":2.1,"targetSharePct":7.1,"receptions":22,"receivingYards":311,"receivingYardsPerGame":19.4,"receivingTouchdowns":1,"catchPct":66.7,"yardsPerReception":14.14,"yardsPerTarget":9.42,"rank":42},{"playerId":"10871","playerName":"Luke Schoonmaker","team":"DAL","games":17,"snapPct":35.1,"fantasyPoints":57.1,"ppg":3.4,"targets":36,"targetsPerGame":2.1,"targetSharePct":6,"receptions":27,"receivingYards":241,"receivingYardsPerGame":14.2,"receivingTouchdowns":1,"catchPct":75,"yardsPerReception":8.93,"yardsPerTarget":6.69,"rank":43},{"playerId":"7694","playerName":"Tommy Tremble","team":"CAR","games":12,"snapPct":68.1,"fantasyPoints":56.4,"ppg":4.7,"targets":32,"targetsPerGame":2.7,"targetSharePct":8.3,"receptions":23,"receivingYards":234,"receivingYardsPerGame":19.5,"receivingTouchdowns":2,"catchPct":71.9,"yardsPerReception":10.17,"yardsPerTarget":7.31,"rank":44},{"playerId":"10231","playerName":"Elijah Higgins","team":"ARI","games":17,"snapPct":37.5,"fantasyPoints":49.2,"ppg":2.9,"targets":24,"targetsPerGame":1.4,"targetSharePct":4.6,"receptions":20,"receivingYards":172,"receivingYardsPerGame":10.1,"receivingTouchdowns":2,"catchPct":83.3,"yardsPerReception":8.6,"yardsPerTarget":7.17,"rank":45},{"playerId":"3258","playerName":"Nick Vannett","team":"TEN","games":17,"snapPct":36.5,"fantasyPoints":48.5,"ppg":2.9,"targets":20,"targetsPerGame":1.2,"targetSharePct":4,"receptions":17,"receivingYards":135,"receivingYardsPerGame":7.9,"receivingTouchdowns":3,"catchPct":85,"yardsPerReception":7.94,"yardsPerTarget":6.75,"rank":46},{"playerId":"4314","playerName":"Johnny Mundt","team":"MIN","games":17,"snapPct":38.9,"fantasyPoints":45.2,"ppg":2.7,"targets":27,"targetsPerGame":1.6,"targetSharePct":5.3,"receptions":19,"receivingYards":142,"receivingYardsPerGame":8.4,"receivingTouchdowns":2,"catchPct":70.4,"yardsPerReception":7.47,"yardsPerTarget":5.26,"rank":47},{"playerId":"9479","playerName":"Darnell Washington","team":"PIT","games":17,"snapPct":51.7,"fantasyPoints":45,"ppg":2.6,"targets":25,"targetsPerGame":1.5,"targetSharePct":5.4,"receptions":19,"receivingYards":200,"receivingYardsPerGame":11.8,"receivingTouchdowns":1,"catchPct":76,"yardsPerReception":10.53,"yardsPerTarget":8,"rank":48},{"playerId":"6869","playerName":"Adam Trautman","team":"DEN","games":17,"snapPct":52.1,"fantasyPoints":43.8,"ppg":2.6,"targets":22,"targetsPerGame":1.3,"targetSharePct":4.1,"receptions":13,"receivingYards":188,"receivingYardsPerGame":11.1,"receivingTouchdowns":2,"catchPct":59.1,"yardsPerReception":14.46,"yardsPerTarget":8.55,"rank":49},{"playerId":"11433","playerName":"Nate Adkins","team":"DEN","games":17,"snapPct":38.1,"fantasyPoints":43.5,"ppg":2.6,"targets":15,"targetsPerGame":0.9,"targetSharePct":2.8,"receptions":14,"receivingYards":115,"receivingYardsPerGame":6.8,"receivingTouchdowns":3,"catchPct":93.3,"yardsPerReception":8.21,"yardsPerTarget":7.67,"rank":50},{"playerId":"5409","playerName":"Tanner Hudson","team":"CIN","games":11,"snapPct":16.3,"fantasyPoints":38.5,"ppg":3.5,"targets":23,"targetsPerGame":2.1,"targetSharePct":5.6,"receptions":19,"receivingYards":154,"receivingYardsPerGame":14,"receivingTouchdowns":1,"catchPct":82.6,"yardsPerReception":8.11,"yardsPerTarget":6.7,"rank":51},{"playerId":"6001","playerName":"Drew Sample","team":"CIN","games":17,"snapPct":57.6,"fantasyPoints":37.5,"ppg":2.2,"targets":22,"targetsPerGame":1.3,"targetSharePct":3.5,"receptions":20,"receivingYards":109,"receivingYardsPerGame":6.4,"receivingTouchdowns":1,"catchPct":90.9,"yardsPerReception":5.45,"yardsPerTarget":4.95,"rank":52},{"playerId":"9482","playerName":"Michael Mayer","team":"LV","games":11,"snapPct":62.8,"fantasyPoints":36.6,"ppg":3.3,"targets":32,"targetsPerGame":2.9,"targetSharePct":8,"receptions":21,"receivingYards":156,"receivingYardsPerGame":14.2,"receivingTouchdowns":0,"catchPct":65.6,"yardsPerReception":7.43,"yardsPerTarget":4.88,"rank":53},{"playerId":"11592","playerName":"Erick All","team":"CIN","games":9,"snapPct":41.9,"fantasyPoints":35.8,"ppg":4,"targets":22,"targetsPerGame":2.4,"targetSharePct":7.6,"receptions":20,"receivingYards":158,"receivingYardsPerGame":17.6,"receivingTouchdowns":0,"catchPct":90.9,"yardsPerReception":7.9,"yardsPerTarget":7.18,"rank":54},{"playerId":"7891","playerName":"Brock Wright","team":"DET","games":17,"snapPct":50.9,"fantasyPoints":35,"ppg":2.1,"targets":16,"targetsPerGame":0.9,"targetSharePct":3.1,"receptions":13,"receivingYards":100,"receivingYardsPerGame":5.9,"receivingTouchdowns":2,"catchPct":81.3,"yardsPerReception":7.69,"yardsPerTarget":6.25,"rank":55},{"playerId":"8583","playerName":"Stone Smartt","team":"LAC","games":14,"snapPct":20,"fantasyPoints":34.8,"ppg":2.5,"targets":19,"targetsPerGame":1.4,"targetSharePct":4.5,"receptions":16,"receivingYards":208,"receivingYardsPerGame":14.9,"receivingTouchdowns":0,"catchPct":84.2,"yardsPerReception":13,"yardsPerTarget":10.95,"rank":56},{"playerId":"10227","playerName":"Payne Durham","team":"TB","games":16,"snapPct":40.6,"fantasyPoints":34.5,"ppg":2.2,"targets":14,"targetsPerGame":0.9,"targetSharePct":2.7,"receptions":11,"receivingYards":115,"receivingYardsPerGame":7.2,"receivingTouchdowns":2,"catchPct":78.6,"yardsPerReception":10.45,"yardsPerTarget":8.21,"rank":57},{"playerId":"11599","playerName":"Cade Stover","team":"HOU","games":15,"snapPct":40.1,"fantasyPoints":34.3,"ppg":2.3,"targets":22,"targetsPerGame":1.5,"targetSharePct":4.5,"receptions":15,"receivingYards":133,"receivingYardsPerGame":8.9,"receivingTouchdowns":1,"catchPct":68.2,"yardsPerReception":8.87,"yardsPerTarget":6.05,"rank":58},{"playerId":"8249","playerName":"Lucas Krull","team":"DEN","games":13,"snapPct":35.5,"fantasyPoints":34.2,"ppg":2.6,"targets":23,"targetsPerGame":1.8,"targetSharePct":5.7,"receptions":19,"receivingYards":152,"receivingYardsPerGame":11.7,"receivingTouchdowns":0,"catchPct":82.6,"yardsPerReception":8,"yardsPerTarget":6.61,"rank":59},{"playerId":"4054","playerName":"Mo Alie-Cox","team":"IND","games":17,"snapPct":43.7,"fantasyPoints":32.7,"ppg":1.9,"targets":22,"targetsPerGame":1.3,"targetSharePct":4.5,"receptions":12,"receivingYards":147,"receivingYardsPerGame":8.6,"receivingTouchdowns":1,"catchPct":54.5,"yardsPerReception":12.25,"yardsPerTarget":6.68,"rank":60},{"playerId":"7602","playerName":"Kylen Granson","team":"IND","games":17,"snapPct":39.6,"fantasyPoints":32.2,"ppg":1.9,"targets":31,"targetsPerGame":1.8,"targetSharePct":6.3,"receptions":14,"receivingYards":182,"receivingYardsPerGame":10.7,"receivingTouchdowns":0,"catchPct":45.2,"yardsPerReception":13,"yardsPerTarget":5.87,"rank":61},{"playerId":"8145","playerName":"Jeremy Ruckert","team":"NYJ","games":17,"snapPct":36.9,"fantasyPoints":28.5,"ppg":1.7,"targets":28,"targetsPerGame":1.6,"targetSharePct":4.8,"receptions":18,"receivingYards":105,"receivingYardsPerGame":6.2,"receivingTouchdowns":0,"catchPct":64.3,"yardsPerReception":5.83,"yardsPerTarget":3.75,"rank":62},{"playerId":"8127","playerName":"Charlie Kolar","team":"BAL","games":13,"snapPct":29.4,"fantasyPoints":28.3,"ppg":2.2,"targets":11,"targetsPerGame":0.8,"targetSharePct":3.1,"receptions":9,"receivingYards":131,"receivingYardsPerGame":10.1,"receivingTouchdowns":1,"catchPct":81.8,"yardsPerReception":14.56,"yardsPerTarget":11.91,"rank":63},{"playerId":"4189","playerName":"Eric Saubert","team":"SF","games":17,"snapPct":34.9,"fantasyPoints":26.7,"ppg":1.6,"targets":14,"targetsPerGame":0.8,"targetSharePct":2.9,"receptions":11,"receivingYards":97,"receivingYardsPerGame":5.7,"receivingTouchdowns":1,"catchPct":78.6,"yardsPerReception":8.82,"yardsPerTarget":6.93,"rank":64},{"playerId":"3271","playerName":"Tyler Higbee","team":"LAR","games":3,"snapPct":33.1,"fantasyPoints":26.6,"ppg":8.9,"targets":12,"targetsPerGame":4,"targetSharePct":13.8,"receptions":8,"receivingYards":66,"receivingYardsPerGame":22,"receivingTouchdowns":2,"catchPct":66.7,"yardsPerReception":8.25,"yardsPerTarget":5.5,"rank":65},{"playerId":"8225","playerName":"Daniel Bellinger","team":"NYG","games":17,"snapPct":32.4,"fantasyPoints":26.5,"ppg":1.6,"targets":17,"targetsPerGame":1,"targetSharePct":3.1,"receptions":14,"receivingYards":125,"receivingYardsPerGame":7.4,"receivingTouchdowns":0,"catchPct":82.4,"yardsPerReception":8.93,"yardsPerTarget":7.35,"rank":66},{"playerId":"8489","playerName":"Drew Ogletree","team":"IND","games":17,"snapPct":40.4,"fantasyPoints":25.9,"ppg":1.5,"targets":14,"targetsPerGame":0.8,"targetSharePct":2.9,"receptions":9,"receivingYards":109,"receivingYardsPerGame":6.4,"receivingTouchdowns":1,"catchPct":64.3,"yardsPerReception":12.11,"yardsPerTarget":7.79,"rank":67},{"playerId":"11371","playerName":"Julian Hill","team":"MIA","games":16,"snapPct":47.7,"fantasyPoints":22,"ppg":1.4,"targets":19,"targetsPerGame":1.2,"targetSharePct":3.6,"receptions":12,"receivingYards":100,"receivingYardsPerGame":6.3,"receivingTouchdowns":0,"catchPct":63.2,"yardsPerReception":8.33,"yardsPerTarget":5.26,"rank":68},{"playerId":"7535","playerName":"Hunter Long","team":"LAR","games":17,"snapPct":25.6,"fantasyPoints":19,"ppg":1.1,"targets":9,"targetsPerGame":0.5,"targetSharePct":1.7,"receptions":7,"receivingYards":60,"receivingYardsPerGame":3.5,"receivingTouchdowns":0,"catchPct":77.8,"yardsPerReception":8.57,"yardsPerTarget":6.67,"rank":69},{"playerId":"7842","playerName":"Luke Farrell","team":"JAX","games":17,"snapPct":37.8,"fantasyPoints":18.7,"ppg":1.1,"targets":17,"targetsPerGame":1,"targetSharePct":3.3,"receptions":12,"receivingYards":67,"receivingYardsPerGame":3.9,"receivingTouchdowns":0,"catchPct":70.6,"yardsPerReception":5.58,"yardsPerTarget":3.94,"rank":70},{"playerId":"11593","playerName":"Brevyn Spann-Ford","team":"DAL","games":17,"snapPct":26,"fantasyPoints":17.8,"ppg":1,"targets":14,"targetsPerGame":0.8,"targetSharePct":2.3,"receptions":9,"receivingYards":88,"receivingYardsPerGame":5.2,"receivingTouchdowns":0,"catchPct":64.3,"yardsPerReception":9.78,"yardsPerTarget":6.29,"rank":71},{"playerId":"6850","playerName":"Harrison Bryant","team":"LV","games":13,"snapPct":24.9,"fantasyPoints":17.6,"ppg":1.4,"targets":12,"targetsPerGame":0.9,"targetSharePct":2.7,"receptions":9,"receivingYards":86,"receivingYardsPerGame":6.6,"receivingTouchdowns":0,"catchPct":75,"yardsPerReception":9.56,"yardsPerTarget":7.17,"rank":72},{"playerId":"11201","playerName":"Blake Whiteheart","team":"CLE","games":11,"snapPct":27.9,"fantasyPoints":17.1,"ppg":1.6,"targets":9,"targetsPerGame":0.8,"targetSharePct":2.3,"receptions":6,"receivingYards":51,"receivingYardsPerGame":4.6,"receivingTouchdowns":1,"catchPct":66.7,"yardsPerReception":8.5,"yardsPerTarget":5.67,"rank":73},{"playerId":"8181","playerName":"Connor Heyward","team":"PIT","games":17,"snapPct":18.3,"fantasyPoints":17,"ppg":1,"targets":8,"targetsPerGame":0.5,"targetSharePct":1.7,"receptions":6,"receivingYards":40,"receivingYardsPerGame":2.4,"receivingTouchdowns":1,"catchPct":75,"yardsPerReception":6.67,"yardsPerTarget":5,"rank":74},{"playerId":"2446","playerName":"MyCole Pruitt","team":"PIT","games":12,"snapPct":34.4,"fantasyPoints":16,"ppg":1.3,"targets":10,"targetsPerGame":0.8,"targetSharePct":3.2,"receptions":6,"receivingYards":40,"receivingYardsPerGame":3.3,"receivingTouchdowns":1,"catchPct":60,"yardsPerReception":6.67,"yardsPerTarget":4,"rank":75},{"playerId":"7597","playerName":"Kenny Yeboah","team":"NYJ","games":9,"snapPct":19,"fantasyPoints":15.7,"ppg":1.7,"targets":8,"targetsPerGame":0.9,"targetSharePct":2.6,"receptions":5,"receivingYards":47,"receivingYardsPerGame":5.2,"receivingTouchdowns":1,"catchPct":62.5,"yardsPerReception":9.4,"yardsPerTarget":5.88,"rank":76},{"playerId":"4973","playerName":"Hayden Hurst","team":"LAC","games":9,"snapPct":31,"fantasyPoints":15.3,"ppg":1.7,"targets":13,"targetsPerGame":1.4,"targetSharePct":5.7,"receptions":8,"receivingYards":73,"receivingYardsPerGame":8.1,"receivingTouchdowns":0,"catchPct":61.5,"yardsPerReception":9.13,"yardsPerTarget":5.62,"rank":77},{"playerId":"7536","playerName":"Quintin Morris","team":"BUF","games":15,"snapPct":22.1,"fantasyPoints":14.6,"ppg":1,"targets":8,"targetsPerGame":0.5,"targetSharePct":1.9,"receptions":5,"receivingYards":36,"receivingYardsPerGame":2.4,"receivingTouchdowns":1,"catchPct":62.5,"yardsPerReception":7.2,"yardsPerTarget":4.5,"rank":78},{"playerId":"7716","playerName":"John Bates","team":"WAS","games":17,"snapPct":44.4,"fantasyPoints":14.4,"ppg":0.8,"targets":13,"targetsPerGame":0.8,"targetSharePct":2.6,"receptions":8,"receivingYards":84,"receivingYardsPerGame":4.9,"receivingTouchdowns":0,"catchPct":61.5,"yardsPerReception":10.5,"yardsPerTarget":6.46,"rank":79},{"playerId":"5008","playerName":"Durham Smythe","team":"MIA","games":17,"snapPct":32,"fantasyPoints":14.3,"ppg":0.8,"targets":17,"targetsPerGame":1,"targetSharePct":3.1,"receptions":9,"receivingYards":53,"receivingYardsPerGame":3.1,"receivingTouchdowns":0,"catchPct":52.9,"yardsPerReception":5.89,"yardsPerTarget":3.12,"rank":80},{"playerId":"11596","playerName":"Ben Sinnott","team":"WAS","games":17,"snapPct":26.7,"fantasyPoints":13.8,"ppg":0.8,"targets":5,"targetsPerGame":0.3,"targetSharePct":1,"receptions":5,"receivingYards":28,"receivingYardsPerGame":1.6,"receivingTouchdowns":1,"catchPct":100,"yardsPerReception":5.6,"yardsPerTarget":5.6,"rank":81},{"playerId":"11820","playerName":"Devin Culp","team":"TB","games":5,"snapPct":11.1,"fantasyPoints":13.8,"ppg":2.8,"targets":6,"targetsPerGame":1.2,"targetSharePct":3,"receptions":5,"receivingYards":88,"receivingYardsPerGame":17.6,"receivingTouchdowns":0,"catchPct":83.3,"yardsPerReception":17.6,"yardsPerTarget":14.67,"rank":82},{"playerId":"4443","playerName":"Pharaoh Brown","team":"SEA","games":15,"snapPct":27.4,"fantasyPoints":12.5,"ppg":0.8,"targets":12,"targetsPerGame":0.8,"targetSharePct":2.4,"receptions":8,"receivingYards":65,"receivingYardsPerGame":4.3,"receivingTouchdowns":0,"catchPct":66.7,"yardsPerReception":8.13,"yardsPerTarget":5.42,"rank":83},{"playerId":"3048","playerName":"Chris Manhertz","team":"NYG","games":17,"snapPct":30.4,"fantasyPoints":12,"ppg":0.7,"targets":4,"targetsPerGame":0.2,"targetSharePct":0.7,"receptions":3,"receivingYards":30,"receivingYardsPerGame":1.8,"receivingTouchdowns":1,"catchPct":75,"yardsPerReception":10,"yardsPerTarget":7.5,"rank":84},{"playerId":"4089","playerName":"Gerald Everett","team":"CHI","games":17,"snapPct":21.7,"fantasyPoints":11.6,"ppg":0.7,"targets":13,"targetsPerGame":0.8,"targetSharePct":2.5,"receptions":8,"receivingYards":36,"receivingYardsPerGame":2.1,"receivingTouchdowns":0,"catchPct":61.5,"yardsPerReception":4.5,"yardsPerTarget":2.77,"rank":85},{"playerId":"7075","playerName":"Charlie Woerner","team":"ATL","games":16,"snapPct":42.2,"fantasyPoints":11.6,"ppg":0.7,"targets":12,"targetsPerGame":0.8,"targetSharePct":2.4,"receptions":7,"receivingYards":46,"receivingYardsPerGame":2.9,"receivingTouchdowns":0,"catchPct":58.3,"yardsPerReception":6.57,"yardsPerTarget":3.83,"rank":86},{"playerId":"9481","playerName":"Luke Musgrave","team":"GB","games":7,"snapPct":30.7,"fantasyPoints":11.5,"ppg":1.6,"targets":10,"targetsPerGame":1.4,"targetSharePct":5,"receptions":7,"receivingYards":45,"receivingYardsPerGame":6.4,"receivingTouchdowns":0,"catchPct":70,"yardsPerReception":6.43,"yardsPerTarget":4.5,"rank":87},{"playerId":"8885","playerName":"Tucker Fisk","team":"LAC","games":9,"snapPct":36,"fantasyPoints":10.9,"ppg":1.2,"targets":8,"targetsPerGame":0.9,"targetSharePct":2.9,"receptions":7,"receivingYards":39,"receivingYardsPerGame":4.3,"receivingTouchdowns":0,"catchPct":87.5,"yardsPerReception":5.57,"yardsPerTarget":4.88,"rank":88},{"playerId":"8197","playerName":"Peyton Hendershot","team":"KC","games":6,"snapPct":18,"fantasyPoints":10.1,"ppg":1.7,"targets":5,"targetsPerGame":0.8,"targetSharePct":2.5,"receptions":5,"receivingYards":51,"receivingYardsPerGame":8.5,"receivingTouchdowns":0,"catchPct":100,"yardsPerReception":10.2,"yardsPerTarget":10.2,"rank":89},{"playerId":"10214","playerName":"Davis Allen","team":"LAR","games":14,"snapPct":33.6,"fantasyPoints":9.9,"ppg":0.7,"targets":13,"targetsPerGame":0.9,"targetSharePct":2.8,"receptions":6,"receivingYards":39,"receivingYardsPerGame":2.8,"receivingTouchdowns":0,"catchPct":46.2,"yardsPerReception":6.5,"yardsPerTarget":3,"rank":90},{"playerId":"11716","playerName":"Tip Reiman","team":"ARI","games":17,"snapPct":41.1,"fantasyPoints":9.7,"ppg":0.6,"targets":7,"targetsPerGame":0.4,"targetSharePct":1.3,"receptions":6,"receivingYards":37,"receivingYardsPerGame":2.2,"receivingTouchdowns":0,"catchPct":85.7,"yardsPerReception":6.17,"yardsPerTarget":5.29,"rank":91},{"playerId":"11082","playerName":"Ben Sims","team":"GB","games":17,"snapPct":20.7,"fantasyPoints":8.2,"ppg":0.5,"targets":5,"targetsPerGame":0.3,"targetSharePct":1.1,"receptions":4,"receivingYards":42,"receivingYardsPerGame":2.5,"receivingTouchdowns":0,"catchPct":80,"yardsPerReception":10.5,"yardsPerTarget":8.4,"rank":92},{"playerId":"8172","playerName":"Greg Dulcich","team":"NYG","games":9,"snapPct":25.7,"fantasyPoints":7.8,"ppg":0.9,"targets":12,"targetsPerGame":1.3,"targetSharePct":4,"receptions":5,"receivingYards":28,"receivingYardsPerGame":3.1,"receivingTouchdowns":0,"catchPct":41.7,"yardsPerReception":5.6,"yardsPerTarget":2.33,"rank":93},{"playerId":"12062","playerName":"Cam Grandy","team":"CIN","games":8,"snapPct":12.8,"fantasyPoints":7.8,"ppg":1,"targets":5,"targetsPerGame":0.6,"targetSharePct":1.5,"receptions":5,"receivingYards":28,"receivingYardsPerGame":3.5,"receivingTouchdowns":0,"catchPct":100,"yardsPerReception":5.6,"yardsPerTarget":5.6,"rank":94},{"playerId":"11304","playerName":"E.J. Jenkins","team":"PHI","games":8,"snapPct":16.6,"fantasyPoints":7.7,"ppg":1,"targets":2,"targetsPerGame":0.3,"targetSharePct":0.9,"receptions":1,"receivingYards":7,"receivingYardsPerGame":0.9,"receivingTouchdowns":1,"catchPct":50,"yardsPerReception":7,"yardsPerTarget":3.5,"rank":95},{"playerId":"10220","playerName":"Will Mallory","team":"IND","games":10,"snapPct":14.3,"fantasyPoints":6.9,"ppg":0.7,"targets":8,"targetsPerGame":0.8,"targetSharePct":2.7,"receptions":4,"receivingYards":29,"receivingYardsPerGame":2.9,"receivingTouchdowns":0,"catchPct":50,"yardsPerReception":7.25,"yardsPerTarget":3.63,"rank":96},{"playerId":"11606","playerName":"Dallin Holker","team":"NO","games":12,"snapPct":9.6,"fantasyPoints":5.1,"ppg":0.4,"targets":4,"targetsPerGame":0.3,"targetSharePct":1.1,"receptions":3,"receivingYards":21,"receivingYardsPerGame":1.8,"receivingTouchdowns":0,"catchPct":75,"yardsPerReception":7,"yardsPerTarget":5.25,"rank":97},{"playerId":"8849","playerName":"Tanner Conner","team":"MIA","games":6,"snapPct":6.5,"fantasyPoints":4.6,"ppg":0.8,"targets":4,"targetsPerGame":0.7,"targetSharePct":2.3,"receptions":3,"receivingYards":16,"receivingYardsPerGame":2.7,"receivingTouchdowns":0,"catchPct":75,"yardsPerReception":5.33,"yardsPerTarget":4,"rank":98},{"playerId":"7050","playerName":"Josiah Deguara","team":"JAX","games":12,"snapPct":11.5,"fantasyPoints":4.4,"ppg":0.4,"targets":3,"targetsPerGame":0.3,"targetSharePct":0.8,"receptions":3,"receivingYards":14,"receivingYardsPerGame":1.2,"receivingTouchdowns":0,"catchPct":100,"yardsPerReception":4.67,"yardsPerTarget":4.67,"rank":99},{"playerId":"11605","playerName":"Jaheim Bell","team":"NE","games":13,"snapPct":9.7,"fantasyPoints":4,"ppg":0.3,"targets":3,"targetsPerGame":0.2,"targetSharePct":0.8,"receptions":2,"receivingYards":20,"receivingYardsPerGame":1.5,"receivingTouchdowns":0,"catchPct":66.7,"yardsPerReception":10,"yardsPerTarget":6.67,"rank":100},{"playerId":"4995","playerName":"Ian Thomas","team":"CAR","games":5,"snapPct":33.2,"fantasyPoints":3.7,"ppg":0.7,"targets":6,"targetsPerGame":1.2,"targetSharePct":4.4,"receptions":3,"receivingYards":7,"receivingYardsPerGame":1.4,"receivingTouchdowns":0,"catchPct":50,"yardsPerReception":2.33,"yardsPerTarget":1.17,"rank":101},{"playerId":"7531","playerName":"Feleipe Franks","team":"CAR","games":13,"snapPct":5.6,"fantasyPoints":3.2,"ppg":0.2,"targets":3,"targetsPerGame":0.2,"targetSharePct":0.8,"receptions":1,"receivingYards":12,"receivingYardsPerGame":0.9,"receivingTouchdowns":0,"catchPct":33.3,"yardsPerReception":12,"yardsPerTarget":4,"rank":102},{"playerId":"8041","playerName":"Shane Zylstra","team":"DET","games":12,"snapPct":13.4,"fantasyPoints":3.2,"ppg":0.3,"targets":1,"targetsPerGame":0.1,"targetSharePct":0.3,"receptions":1,"receivingYards":22,"receivingYardsPerGame":1.8,"receivingTouchdowns":0,"catchPct":100,"yardsPerReception":22,"yardsPerTarget":22,"rank":103},{"playerId":"7946","playerName":"Jack Stoll","team":"MIA","games":9,"snapPct":34.3,"fantasyPoints":3,"ppg":0.3,"targets":3,"targetsPerGame":0.3,"targetSharePct":1.4,"receptions":2,"receivingYards":10,"receivingYardsPerGame":1.1,"receivingTouchdowns":0,"catchPct":66.7,"yardsPerReception":5,"yardsPerTarget":3.33,"rank":104},{"playerId":"2755","playerName":"Eric Tomlinson","team":"LAC","games":9,"snapPct":24.3,"fantasyPoints":2.9,"ppg":0.3,"targets":4,"targetsPerGame":0.4,"targetSharePct":1.6,"receptions":2,"receivingYards":9,"receivingYardsPerGame":1,"receivingTouchdowns":0,"catchPct":50,"yardsPerReception":4.5,"yardsPerTarget":2.25,"rank":105},{"playerId":"7568","playerName":"Brevin Jordan","team":"HOU","games":2,"snapPct":47.5,"fantasyPoints":2.7,"ppg":1.4,"targets":3,"targetsPerGame":1.5,"targetSharePct":4.6,"receptions":2,"receivingYards":7,"receivingYardsPerGame":3.5,"receivingTouchdowns":0,"catchPct":66.7,"yardsPerReception":3.5,"yardsPerTarget":2.33,"rank":106},{"playerId":"2545","playerName":"Geoff Swaim","team":"CLE","games":8,"snapPct":25.3,"fantasyPoints":1.7,"ppg":0.2,"targets":1,"targetsPerGame":0.1,"targetSharePct":0.3,"receptions":1,"receivingYards":7,"receivingYardsPerGame":0.9,"receivingTouchdowns":0,"catchPct":100,"yardsPerReception":7,"yardsPerTarget":7,"rank":107},{"playerId":"11467","playerName":"John Samuel Shenker","team":"LV","games":7,"snapPct":13.5,"fantasyPoints":1.7,"ppg":0.2,"targets":1,"targetsPerGame":0.1,"targetSharePct":0.4,"receptions":1,"receivingYards":7,"receivingYardsPerGame":1,"receivingTouchdowns":0,"catchPct":100,"yardsPerReception":7,"yardsPerTarget":7,"rank":108},{"playerId":"11595","playerName":"Jared Wiley","team":"KC","games":7,"snapPct":19.5,"fantasyPoints":1.7,"ppg":0.2,"targets":1,"targetsPerGame":0.1,"targetSharePct":0.5,"receptions":1,"receivingYards":7,"receivingYardsPerGame":1,"receivingTouchdowns":0,"catchPct":100,"yardsPerReception":7,"yardsPerTarget":7,"rank":109},{"playerId":"12357","playerName":"David Martin-Robinson","team":"TEN","games":5,"snapPct":14.1,"fantasyPoints":1.6,"ppg":0.3,"targets":2,"targetsPerGame":0.4,"targetSharePct":1.3,"receptions":1,"receivingYards":6,"receivingYardsPerGame":1.2,"receivingTouchdowns":0,"catchPct":50,"yardsPerReception":6,"yardsPerTarget":3,"rank":110},{"playerId":"5285","playerName":"Ross Dwelley","team":"ATL","games":14,"snapPct":11.5,"fantasyPoints":1.5,"ppg":0.1,"targets":1,"targetsPerGame":0.1,"targetSharePct":0.2,"receptions":1,"receivingYards":5,"receivingYardsPerGame":0.4,"receivingTouchdowns":0,"catchPct":100,"yardsPerReception":5,"yardsPerTarget":5,"rank":111},{"playerId":"6665","playerName":"Jody Fortson","team":"KC","games":3,"snapPct":17.7,"fantasyPoints":1.5,"ppg":0.5,"targets":3,"targetsPerGame":1,"targetSharePct":3.2,"receptions":1,"receivingYards":5,"receivingYardsPerGame":1.7,"receivingTouchdowns":0,"catchPct":33.3,"yardsPerReception":5,"yardsPerTarget":1.67,"rank":112},{"playerId":"7943","playerName":"Zach Davidson","team":"BUF","games":2,"snapPct":20.3,"fantasyPoints":1.5,"ppg":0.8,"targets":1,"targetsPerGame":0.5,"targetSharePct":1.3,"receptions":1,"receivingYards":5,"receivingYardsPerGame":2.5,"receivingTouchdowns":0,"catchPct":100,"yardsPerReception":5,"yardsPerTarget":5,"rank":113},{"playerId":"111","playerName":"Marcedes Lewis","team":"CHI","games":17,"snapPct":19.4,"fantasyPoints":1.2,"ppg":0.1,"targets":2,"targetsPerGame":0.1,"targetSharePct":0.4,"receptions":1,"receivingYards":2,"receivingYardsPerGame":0.1,"receivingTouchdowns":0,"catchPct":50,"yardsPerReception":2,"yardsPerTarget":1,"rank":114},{"playerId":"8500","playerName":"John FitzPatrick","team":"GB","games":9,"snapPct":12.9,"fantasyPoints":1.2,"ppg":0.1,"targets":1,"targetsPerGame":0.1,"targetSharePct":0.4,"receptions":1,"receivingYards":2,"receivingYardsPerGame":0.2,"receivingTouchdowns":0,"catchPct":100,"yardsPerReception":2,"yardsPerTarget":2,"rank":115},{"playerId":"1800","playerName":"Jordan Matthews","team":"CAR","games":3,"snapPct":16.3,"fantasyPoints":0,"ppg":0,"targets":1,"targetsPerGame":0.3,"targetSharePct":1.3,"receptions":0,"receivingYards":0,"receivingYardsPerGame":0,"receivingTouchdowns":0,"catchPct":0,"yardsPerReception":null,"yardsPerTarget":0,"rank":116},{"playerId":"2460","playerName":"C.J. Uzomah","team":"PHI","games":7,"snapPct":27.7,"fantasyPoints":0,"ppg":0,"targets":0,"targetsPerGame":0,"targetSharePct":0,"receptions":0,"receivingYards":0,"receivingYardsPerGame":0,"receivingTouchdowns":0,"catchPct":null,"yardsPerReception":null,"yardsPerTarget":null,"rank":117},{"playerId":"4435","playerName":"Anthony Firkser","team":"KC","games":6,"snapPct":8.3,"fantasyPoints":0,"ppg":0,"targets":0,"targetsPerGame":0,"targetSharePct":0,"receptions":0,"receivingYards":0,"receivingYardsPerGame":0,"receivingTouchdowns":0,"catchPct":null,"yardsPerReception":null,"yardsPerTarget":null,"rank":118},{"playerId":"4602","playerName":"Robert Tonyan","team":"MIN","games":5,"snapPct":4.8,"fantasyPoints":0,"ppg":0,"targets":0,"targetsPerGame":0,"targetSharePct":0,"receptions":0,"receivingYards":0,"receivingYardsPerGame":0,"receivingTouchdowns":0,"catchPct":null,"yardsPerReception":null,"yardsPerTarget":null,"rank":119},{"playerId":"6126","playerName":"Irv Smith","team":"HOU","games":5,"snapPct":29.5,"fantasyPoints":0,"ppg":0,"targets":0,"targetsPerGame":0,"targetSharePct":0,"receptions":0,"receivingYards":0,"receivingYardsPerGame":0,"receivingTouchdowns":0,"catchPct":null,"yardsPerReception":null,"yardsPerTarget":null,"rank":120},{"playerId":"6662","playerName":"Parker Hesse","team":"DET","games":5,"snapPct":17.6,"fantasyPoints":0,"ppg":0,"targets":0,"targetsPerGame":0,"targetSharePct":0,"receptions":0,"receivingYards":0,"receivingYardsPerGame":0,"receivingTouchdowns":0,"catchPct":null,"yardsPerReception":null,"yardsPerTarget":null,"rank":121},{"playerId":"6894","playerName":"Mitchell Wilcox","team":"NE","games":1,"snapPct":1.6,"fantasyPoints":0,"ppg":0,"targets":0,"targetsPerGame":0,"targetSharePct":0,"receptions":0,"receivingYards":0,"receivingYardsPerGame":0,"receivingTouchdowns":0,"catchPct":null,"yardsPerReception":null,"yardsPerTarget":null,"rank":122},{"playerId":"6970","playerName":"Stephen Sullivan","team":"CAR","games":1,"snapPct":11.4,"fantasyPoints":0,"ppg":0,"targets":1,"targetsPerGame":1,"targetSharePct":2.4,"receptions":0,"receivingYards":0,"receivingYardsPerGame":0,"receivingTouchdowns":0,"catchPct":0,"yardsPerReception":null,"yardsPerTarget":0,"rank":123},{"playerId":"7427","playerName":"Tyler Mabry","team":"SEA","games":2,"snapPct":3.2,"fantasyPoints":0,"ppg":0,"targets":0,"targetsPerGame":0,"targetSharePct":0,"receptions":0,"receivingYards":0,"receivingYardsPerGame":0,"receivingTouchdowns":0,"catchPct":null,"yardsPerReception":null,"yardsPerTarget":null,"rank":124},{"playerId":"8170","playerName":"James Mitchell","team":"DET","games":1,"snapPct":31.6,"fantasyPoints":0,"ppg":0,"targets":0,"targetsPerGame":0,"targetSharePct":0,"receptions":0,"receivingYards":0,"receivingYardsPerGame":0,"receivingTouchdowns":0,"catchPct":null,"yardsPerReception":null,"yardsPerTarget":null,"rank":125},{"playerId":"8227","playerName":"Teagan Quitoriano","team":"HOU","games":7,"snapPct":21.8,"fantasyPoints":0,"ppg":0,"targets":0,"targetsPerGame":0,"targetSharePct":0,"receptions":0,"receivingYards":0,"receivingYardsPerGame":0,"receivingTouchdowns":0,"catchPct":null,"yardsPerReception":null,"yardsPerTarget":null,"rank":126},{"playerId":"8484","playerName":"Ko Kieft","team":"TB","games":17,"snapPct":9.1,"fantasyPoints":0,"ppg":0,"targets":0,"targetsPerGame":0,"targetSharePct":0,"receptions":0,"receivingYards":0,"receivingYardsPerGame":0,"receivingTouchdowns":0,"catchPct":null,"yardsPerReception":null,"yardsPerTarget":null,"rank":127},{"playerId":"8523","playerName":"Nick Muse","team":"MIN","games":3,"snapPct":9.5,"fantasyPoints":0,"ppg":0,"targets":0,"targetsPerGame":0,"targetSharePct":0,"receptions":0,"receivingYards":0,"receivingYardsPerGame":0,"receivingTouchdowns":0,"catchPct":null,"yardsPerReception":null,"yardsPerTarget":null,"rank":128},{"playerId":"8660","playerName":"Leroy Watson","team":"TEN","games":4,"snapPct":71.7,"fantasyPoints":0,"ppg":0,"targets":0,"targetsPerGame":0,"targetSharePct":0,"receptions":0,"receivingYards":0,"receivingYardsPerGame":0,"receivingTouchdowns":0,"catchPct":null,"yardsPerReception":null,"yardsPerTarget":null,"rank":129},{"playerId":"8698","playerName":"Jake Tonges","team":"SF","games":11,"snapPct":4.7,"fantasyPoints":0,"ppg":0,"targets":0,"targetsPerGame":0,"targetSharePct":0,"receptions":0,"receivingYards":0,"receivingYardsPerGame":0,"receivingTouchdowns":0,"catchPct":null,"yardsPerReception":null,"yardsPerTarget":null,"rank":130},{"playerId":"8757","playerName":"Rodney Williams","team":"PIT","games":3,"snapPct":2.5,"fantasyPoints":0,"ppg":0,"targets":0,"targetsPerGame":0,"targetSharePct":0,"receptions":0,"receivingYards":0,"receivingYardsPerGame":0,"receivingTouchdowns":0,"catchPct":null,"yardsPerReception":null,"yardsPerTarget":null,"rank":131},{"playerId":"9483","playerName":"Zack Kuntz","team":"NYJ","games":1,"snapPct":1.7,"fantasyPoints":0,"ppg":0,"targets":0,"targetsPerGame":0,"targetSharePct":0,"receptions":0,"receivingYards":0,"receivingYardsPerGame":0,"receivingTouchdowns":0,"catchPct":null,"yardsPerReception":null,"yardsPerTarget":null,"rank":132},{"playerId":"10224","playerName":"Brayden Willis","team":"SF","games":7,"snapPct":5.5,"fantasyPoints":0,"ppg":0,"targets":2,"targetsPerGame":0.3,"targetSharePct":1,"receptions":0,"receivingYards":0,"receivingYardsPerGame":0,"receivingTouchdowns":0,"catchPct":0,"yardsPerReception":null,"yardsPerTarget":0,"rank":133},{"playerId":"11280","playerName":"Brady Russell","team":"SEA","games":9,"snapPct":5.3,"fantasyPoints":0,"ppg":0,"targets":0,"targetsPerGame":0,"targetSharePct":0,"receptions":0,"receivingYards":0,"receivingYardsPerGame":0,"receivingTouchdowns":0,"catchPct":null,"yardsPerReception":null,"yardsPerTarget":null,"rank":134},{"playerId":"11381","playerName":"Travis Vokolek","team":"ARI","games":1,"snapPct":20.3,"fantasyPoints":0,"ppg":0,"targets":0,"targetsPerGame":0,"targetSharePct":0,"receptions":0,"receivingYards":0,"receivingYardsPerGame":0,"receivingTouchdowns":0,"catchPct":null,"yardsPerReception":null,"yardsPerTarget":null,"rank":135},{"playerId":"11508","playerName":"Princeton Fant","team":"DAL","games":4,"snapPct":4.8,"fantasyPoints":0,"ppg":0,"targets":0,"targetsPerGame":0,"targetSharePct":0,"receptions":0,"receivingYards":0,"receivingYardsPerGame":0,"receivingTouchdowns":0,"catchPct":null,"yardsPerReception":null,"yardsPerTarget":null,"rank":136},{"playerId":"11598","playerName":"Tanner McLachlan","team":"CIN","games":2,"snapPct":3.4,"fantasyPoints":0,"ppg":0,"targets":0,"targetsPerGame":0,"targetSharePct":0,"receptions":0,"receivingYards":0,"receivingYardsPerGame":0,"receivingTouchdowns":0,"catchPct":null,"yardsPerReception":null,"yardsPerTarget":null,"rank":137},{"playerId":"11942","playerName":"Colson Yankoff","team":"WAS","games":2,"snapPct":4.4,"fantasyPoints":0,"ppg":0,"targets":0,"targetsPerGame":0,"targetSharePct":0,"receptions":0,"receivingYards":0,"receivingYardsPerGame":0,"receivingTouchdowns":0,"catchPct":null,"yardsPerReception":null,"yardsPerTarget":null,"rank":138},{"playerId":"12045","playerName":"Jack Westover","team":"NE","games":2,"snapPct":6.8,"fantasyPoints":0,"ppg":0,"targets":0,"targetsPerGame":0,"targetSharePct":0,"receptions":0,"receivingYards":0,"receivingYardsPerGame":0,"receivingTouchdowns":0,"catchPct":null,"yardsPerReception":null,"yardsPerTarget":null,"rank":139},{"playerId":"12256","playerName":"Baylor Cupp","team":"KC","games":1,"snapPct":8.7,"fantasyPoints":0,"ppg":0,"targets":1,"targetsPerGame":1,"targetSharePct":2.8,"receptions":0,"receivingYards":0,"receivingYardsPerGame":0,"receivingTouchdowns":0,"catchPct":0,"yardsPerReception":null,"yardsPerTarget":0,"rank":140},{"playerId":"12374","playerName":"Brenden Bates","team":"CLE","games":6,"snapPct":9.9,"fantasyPoints":0,"ppg":0,"targets":1,"targetsPerGame":0.2,"targetSharePct":0.4,"receptions":0,"receivingYards":0,"receivingYardsPerGame":0,"receivingTouchdowns":0,"catchPct":0,"yardsPerReception":null,"yardsPerTarget":0,"rank":141}]}