{"neighbors":[{"id":"8145","name":"Jeremy Ruckert","slug":"jeremy-ruckert","team":"NYJ","position":"TE","posRank":58,"ppg":2.9},{"id":"6869","name":"Adam Trautman","slug":"adam-trautman","team":"DEN","position":"TE","posRank":59,"ppg":2.8},{"id":"12521","name":"Elijah Arroyo","slug":"elijah-arroyo","team":"SEA","position":"TE","posRank":60,"ppg":2.8},{"id":"7828","name":"Noah Gray","slug":"noah-gray","team":"KC","position":"TE","posRank":62,"ppg":2.4},{"id":"5010","name":"Will Dissly","slug":"will-dissly","team":"LAC","position":"TE","posRank":63,"ppg":2.3},{"id":"8127","name":"Charlie Kolar","slug":"charlie-kolar","team":"BAL","position":"TE","posRank":64,"ppg":2.3}],"currentRank":61,"season":2025,"format":"ppr","position":"TE"}