{"neighbors":[{"id":"12512","name":"Quinshon Judkins","slug":"quinshon-judkins","team":"CLE","position":"RB","posRank":25,"ppg":10.1},{"id":"9753","name":"Zach Charbonnet","slug":"zach-charbonnet","team":"SEA","position":"RB","posRank":26,"ppg":10},{"id":"12489","name":"RJ Harvey","slug":"rj-harvey","team":"DEN","position":"RB","posRank":27,"ppg":9.5},{"id":"5967","name":"Tony Pollard","slug":"tony-pollard","team":"TEN","position":"RB","posRank":29,"ppg":9.3},{"id":"7567","name":"Kenneth Gainwell","slug":"kenneth-gainwell","team":"PIT","position":"RB","posRank":30,"ppg":8.8},{"id":"11655","name":"Tyrone Tracy","slug":"tyrone-tracy","team":"NYG","position":"RB","posRank":31,"ppg":8.5}],"currentRank":28,"season":2025,"format":"standard","position":"RB"}